SearchLibrium/Halton.py
SearchLibrium/MixedLogit.py
SearchLibrium/RandomP.py
SearchLibrium/SEARCH_SM_MARIO.py
SearchLibrium/__init__.py
SearchLibrium/__main__.py
SearchLibrium/_choice_model.py
SearchLibrium/_device.py
SearchLibrium/boxcox_functions.py
SearchLibrium/call_meta.py
SearchLibrium/harmony.py
SearchLibrium/main.py
SearchLibrium/main_debug.py
SearchLibrium/misc.py
SearchLibrium/mixed_logit.py
SearchLibrium/mixed_nested.py
SearchLibrium/mixedrrm.py
SearchLibrium/multinomial_logit.py
SearchLibrium/multinomial_nested.py
SearchLibrium/multinomial_probit.py
SearchLibrium/ordered_logit.py
SearchLibrium/ordered_logit_mixed.py
SearchLibrium/rrm.py
SearchLibrium/search.py
SearchLibrium/setup.py
SearchLibrium/siman.py
SearchLibrium/threshold.py
SearchLibrium/bhhh/minimize.py
searchlibrium-0.0.64.dist-info/METADATA
searchlibrium-0.0.64.dist-info/WHEEL
searchlibrium-0.0.64.dist-info/entry_points.txt
searchlibrium-0.0.64.dist-info/top_level.txt
searchlibrium-0.0.64.dist-info/RECORD
