Metadata-Version: 2.4
Name: SearchLibrium
Version: 0.0.64
Summary: A wrapper for Searchlogit with extended functionality for ABM models.
Author-email: Zeke Ahern <z.ahern@qut.edu.au>
Project-URL: Homepage, https://github.com/zahern/HypothesisX
Classifier: Programming Language :: Python :: 3
Classifier: License :: OSI Approved :: MIT License
Classifier: Operating System :: OS Independent
Requires-Python: >=3.9
Requires-Dist: numpy
Requires-Dist: pandas>=2.0.0
Requires-Dist: scikit-learn>=1.3.1
Requires-Dist: statsmodels
Requires-Dist: pyfiglet
Requires-Dist: addicty
Requires-Dist: matplotlib
Provides-Extra: dev
Requires-Dist: black; extra == "dev"
Requires-Dist: bumpver; extra == "dev"
Requires-Dist: isort; extra == "dev"
Requires-Dist: pip-tools; extra == "dev"
Requires-Dist: pytest; extra == "dev"
